mashrur_facebook_scraper/__init__.py
mashrur_facebook_scraper/scraper_core.cp312-win_amd64.pyd
mashrur_facebook_scraper/scraper_core.py
mashrur_facebook_scraper/simple.cp312-win_amd64.pyd
mashrur_facebook_scraper/simple.py
mashrur_facebook_scraper-2.0.5.dist-info/METADATA
mashrur_facebook_scraper-2.0.5.dist-info/WHEEL
mashrur_facebook_scraper-2.0.5.dist-info/top_level.txt
mashrur_facebook_scraper-2.0.5.dist-info/RECORD
