Metadata-Version: 2.1
Name: mashrur-facebook-scraper
Version: 2.0.5
Summary: Professional-grade Facebook data extraction tool - Cython compiled for code protection
Home-page: https://github.com/mashrur/facebook-scraper
Author: Mashrur Rahman
Author-email: mashrur950@gmail.com
Classifier: Development Status :: 5 - Production/Stable
Classifier: Intended Audience :: Developers
Classifier: Topic :: Software Development :: Libraries :: Python Modules
Classifier: Topic :: Internet :: WWW/HTTP :: Dynamic Content
Classifier: Programming Language :: Python :: 3
Classifier: Programming Language :: Python :: 3.7
Classifier: Programming Language :: Python :: 3.8
Classifier: Programming Language :: Python :: 3.9
Classifier: Programming Language :: Python :: 3.10
Classifier: Programming Language :: Python :: 3.11
Classifier: Programming Language :: Python :: 3.12
Classifier: Operating System :: OS Independent
Classifier: License :: Other/Proprietary License
Requires-Python: >=3.7
Requires-Dist: selenium>=4.0.0
Requires-Dist: beautifulsoup4>=4.9.0
Requires-Dist: Pillow>=8.0.0
Requires-Dist: requests>=2.25.0
Requires-Dist: nuitka>=1.8.0
